_amplpy_copt_swig.cpython-38-darwin.so
amplpy_copt-0.2.1.dist-info/RECORD
amplpy_copt-0.2.1.dist-info/LICENSE
amplpy_copt-0.2.1.dist-info/WHEEL
amplpy_copt-0.2.1.dist-info/top_level.txt
amplpy_copt-0.2.1.dist-info/METADATA
amplpy_copt/patch.py
amplpy_copt/__init__.py
amplpy_copt/.gitignore
amplpy_copt/swig/copt-python-overrides.i
amplpy_copt/swig/amplpy_copt_swig.py
amplpy_copt/swig/amplpy_copt_swig.i
amplpy_copt/swig/amplpy_copt_swig_wrap.h
amplpy_copt/swig/amplpy_copt_swig_wrap.cxx
amplpy_copt/tests/test_callbacks.py
amplpy_copt/tests/test_cuttingstock.py
amplpy_copt/tests/test_options.py
amplpy_copt/tests/__init__.py
amplpy_copt/tests/tsp_helpers.py
amplpy_copt/tests/test_multiple_models.py
amplpy_copt/tests/test_base.py
amplpy_copt/tests/__main__.py
amplpy_copt/tests/test_multiple_solutions.py
amplpy_copt/tests/test_tsp.py
amplpy_copt/tests/data/tsp_40_1.txt
amplpy_copt/tests/data/queens.mod
amplpy_copt/libs/copt/include/.gitignore
amplpy_copt/libs/copt/include/copt.h
amplpy_copt/libs/copt/lib/osx64/libcrypto.a
amplpy_copt/libs/copt/lib/osx64/libcoptoem.a
amplpy_copt/libs/copt/lib/osx64/libcopt.dylib
amplpy_copt/libs/copt/lib/osx64/.gitignore
amplpy_copt/libs/copt/lib/osx64/libssl.a
amplpy_copt/libs/copt/lib/osx64/libcopt-lib.dylib
amplpy_copt/cpp/copt/swig/copt-common.i
amplpy_copt/cpp/copt/test/copt-test.cpp
amplpy_copt/cpp/copt/include/copt_callback.h
amplpy_copt/cpp/copt/include/copt_interface.h
amplpy_copt/cpp/copt/examples/simpleCuts.cpp
amplpy_copt/cpp/copt/examples/loadModel.cpp
amplpy_copt/cpp/copt/examples/getInformation.cpp
amplpy_copt/cpp/copt/src/copt_callback.cpp
amplpy_copt/cpp/copt/src/copt_interface.cpp
amplpy_copt/cpp/ampls/CMakeLists.txt
amplpy_copt/cpp/ampls/swig/ampls-common.i
amplpy_copt/cpp/ampls/test/test-base.h
amplpy_copt/cpp/ampls/test/multipleModels-test.cpp
amplpy_copt/cpp/ampls/test/setOptions-test.cpp
amplpy_copt/cpp/ampls/test/getInformation-test.cpp
amplpy_copt/cpp/ampls/test/test-execute.h
amplpy_copt/cpp/ampls/test/cuttingStock-test.cpp
amplpy_copt/cpp/ampls/test/errorDetection-test.cpp
amplpy_copt/cpp/ampls/test/multipleSolutions-test.cpp
